{"@t":"2021-01-29T10:01:57.2192659Z","@mt":"{StartMessage} [Timing {TimingId}]","StartMessage":"Booting Umbraco 8.10.1.","TimingId":"6caa470","SourceContext":"Umbraco.Core.Runtime.CoreRuntime","ProcessId":14928,"ProcessName":"w3wp","ThreadId":1,"AppDomainId":2,"AppDomainAppId":"LMW3SVC2ROOT","MachineName":"DESKTOP-10GN34Q","Log4NetLevel":"INFO ","HttpRequestNumber":1,"HttpRequestId":"c0249f4d-5b93-4c68-a218-0352480ca04c"}
{"@t":"2021-01-29T10:01:57.2451918Z","@mt":"Booting site '{HostingSiteName}', app '{HostingApplicationID}', path '{HostingPhysicalPath}', server '{MachineName}'.","HostingSiteName":"TreasureRoom","HostingApplicationID":"/LM/W3SVC/2/ROOT","HostingPhysicalPath":"C:\\Users\\Aryan Dang\\Desktop\\Treasure Room\\TreasureRoom\\TreasureRoom\\","MachineName":"DESKTOP-10GN34Q","SourceContext":"Umbraco.Core.Runtime.CoreRuntime","ProcessId":14928,"ProcessName":"w3wp","ThreadId":1,"AppDomainId":2,"AppDomainAppId":"LMW3SVC2ROOT","Log4NetLevel":"INFO ","HttpRequestNumber":1,"HttpRequestId":"c0249f4d-5b93-4c68-a218-0352480ca04c"}
{"@t":"2021-01-29T10:01:57.3927704Z","@mt":"Acquiring.","SourceContext":"Umbraco.Core.Runtime.MainDom","ProcessId":14928,"ProcessName":"w3wp","ThreadId":1,"AppDomainId":2,"AppDomainAppId":"LMW3SVC2ROOT","MachineName":"DESKTOP-10GN34Q","Log4NetLevel":"INFO ","HttpRequestNumber":1,"HttpRequestId":"c0249f4d-5b93-4c68-a218-0352480ca04c"}
{"@t":"2021-01-29T10:01:57.3947657Z","@mt":"Acquired.","SourceContext":"Umbraco.Core.Runtime.MainDom","ProcessId":14928,"ProcessName":"w3wp","ThreadId":1,"AppDomainId":2,"AppDomainAppId":"LMW3SVC2ROOT","MachineName":"DESKTOP-10GN34Q","Log4NetLevel":"INFO ","HttpRequestNumber":1,"HttpRequestId":"c0249f4d-5b93-4c68-a218-0352480ca04c"}
{"@t":"2021-01-29T10:01:58.2654673Z","@mt":"{StartMessage} [Timing {TimingId}]","StartMessage":"Resolving composer types.","TimingId":"75cf449","SourceContext":"Umbraco.Core.Runtime.CoreRuntime","ProcessId":14928,"ProcessName":"w3wp","ThreadId":1,"AppDomainId":2,"AppDomainAppId":"LMW3SVC2ROOT","MachineName":"DESKTOP-10GN34Q","Log4NetLevel":"INFO ","HttpRequestNumber":1,"HttpRequestId":"c0249f4d-5b93-4c68-a218-0352480ca04c"}
{"@t":"2021-01-29T10:01:58.4986673Z","@mt":"{EndMessage} ({Duration}ms) [Timing {TimingId}]","EndMessage":"Resolved.","Duration":232,"TimingId":"75cf449","SourceContext":"Umbraco.Core.Runtime.CoreRuntime","ProcessId":14928,"ProcessName":"w3wp","ThreadId":1,"AppDomainId":2,"AppDomainAppId":"LMW3SVC2ROOT","MachineName":"DESKTOP-10GN34Q","Log4NetLevel":"INFO ","HttpRequestNumber":1,"HttpRequestId":"c0249f4d-5b93-4c68-a218-0352480ca04c"}
{"@t":"2021-01-29T10:02:01.9183847Z","@mt":"ModelsBuilder.Embedded is disabled, the external ModelsBuilder was detected.","SourceContext":"Umbraco.ModelsBuilder.Embedded.Compose.ModelsBuilderComposer","ProcessId":14928,"ProcessName":"w3wp","ThreadId":1,"AppDomainId":2,"AppDomainAppId":"LMW3SVC2ROOT","MachineName":"DESKTOP-10GN34Q","Log4NetLevel":"INFO ","HttpRequestNumber":1,"HttpRequestId":"c0249f4d-5b93-4c68-a218-0352480ca04c"}
{"@t":"2021-01-29T10:02:02.5855685Z","@mt":"Registered with MainDom, localContentDbExists? {LocalContentDbExists}, localMediaDbExists? {LocalMediaDbExists}","LocalContentDbExists":true,"LocalMediaDbExists":true,"SourceContext":"Umbraco.Web.PublishedCache.NuCache.PublishedSnapshotService","ProcessId":14928,"ProcessName":"w3wp","ThreadId":1,"AppDomainId":2,"AppDomainAppId":"LMW3SVC2ROOT","MachineName":"DESKTOP-10GN34Q","Log4NetLevel":"INFO ","HttpRequestNumber":1,"HttpRequestId":"c0249f4d-5b93-4c68-a218-0352480ca04c"}
{"@t":"2021-01-29T10:02:02.5855685Z","@mt":"Creating the content store, localContentDbExists? {LocalContentDbExists}","LocalContentDbExists":true,"SourceContext":"Umbraco.Web.PublishedCache.NuCache.PublishedSnapshotService","ProcessId":14928,"ProcessName":"w3wp","ThreadId":1,"AppDomainId":2,"AppDomainAppId":"LMW3SVC2ROOT","MachineName":"DESKTOP-10GN34Q","Log4NetLevel":"INFO ","HttpRequestNumber":1,"HttpRequestId":"c0249f4d-5b93-4c68-a218-0352480ca04c"}
{"@t":"2021-01-29T10:02:02.5865661Z","@mt":"Creating the media store, localMediaDbExists? {LocalMediaDbExists}","LocalMediaDbExists":true,"SourceContext":"Umbraco.Web.PublishedCache.NuCache.PublishedSnapshotService","ProcessId":14928,"ProcessName":"w3wp","ThreadId":1,"AppDomainId":2,"AppDomainAppId":"LMW3SVC2ROOT","MachineName":"DESKTOP-10GN34Q","Log4NetLevel":"INFO ","HttpRequestNumber":1,"HttpRequestId":"c0249f4d-5b93-4c68-a218-0352480ca04c"}
{"@t":"2021-01-29T10:02:03.2705833Z","@mt":"Could not find an editor with alias {EditorAlias}, treating as Label. The site may fail to boot and / or load data types and run.","@l":"Warning","EditorAlias":"UmbracoForms.FormPicker","SourceContext":"Umbraco.Core.Models.DataType","ProcessId":14928,"ProcessName":"w3wp","ThreadId":1,"AppDomainId":2,"AppDomainAppId":"LMW3SVC2ROOT","MachineName":"DESKTOP-10GN34Q","Log4NetLevel":"WARN ","HttpRequestNumber":1,"HttpRequestId":"c0249f4d-5b93-4c68-a218-0352480ca04c"}
{"@t":"2021-01-29T10:02:03.2845778Z","@mt":"{StartMessage} [Timing {TimingId}]","StartMessage":"Loading content from local cache file","TimingId":"a991b08","SourceContext":"Umbraco.Web.PublishedCache.NuCache.PublishedSnapshotService","ProcessId":14928,"ProcessName":"w3wp","ThreadId":1,"AppDomainId":2,"AppDomainAppId":"LMW3SVC2ROOT","MachineName":"DESKTOP-10GN34Q","Log4NetLevel":"INFO ","HttpRequestNumber":1,"HttpRequestId":"c0249f4d-5b93-4c68-a218-0352480ca04c"}
{"@t":"2021-01-29T10:02:03.3214488Z","@mt":"{EndMessage} ({Duration}ms) [Timing {TimingId}]","EndMessage":"Completed.","Duration":37,"TimingId":"a991b08","SourceContext":"Umbraco.Web.PublishedCache.NuCache.PublishedSnapshotService","ProcessId":14928,"ProcessName":"w3wp","ThreadId":1,"AppDomainId":2,"AppDomainAppId":"LMW3SVC2ROOT","MachineName":"DESKTOP-10GN34Q","Log4NetLevel":"INFO ","HttpRequestNumber":1,"HttpRequestId":"c0249f4d-5b93-4c68-a218-0352480ca04c"}
{"@t":"2021-01-29T10:02:03.3364074Z","@mt":"{StartMessage} [Timing {TimingId}]","StartMessage":"Loading media from local cache file","TimingId":"acbe3f5","SourceContext":"Umbraco.Web.PublishedCache.NuCache.PublishedSnapshotService","ProcessId":14928,"ProcessName":"w3wp","ThreadId":1,"AppDomainId":2,"AppDomainAppId":"LMW3SVC2ROOT","MachineName":"DESKTOP-10GN34Q","Log4NetLevel":"INFO ","HttpRequestNumber":1,"HttpRequestId":"c0249f4d-5b93-4c68-a218-0352480ca04c"}
{"@t":"2021-01-29T10:02:03.3374050Z","@mt":"{EndMessage} ({Duration}ms) [Timing {TimingId}]","EndMessage":"Completed.","Duration":0,"TimingId":"acbe3f5","SourceContext":"Umbraco.Web.PublishedCache.NuCache.PublishedSnapshotService","ProcessId":14928,"ProcessName":"w3wp","ThreadId":1,"AppDomainId":2,"AppDomainAppId":"LMW3SVC2ROOT","MachineName":"DESKTOP-10GN34Q","Log4NetLevel":"INFO ","HttpRequestNumber":1,"HttpRequestId":"c0249f4d-5b93-4c68-a218-0352480ca04c"}
{"@t":"2021-01-29T10:02:03.5787318Z","@mt":"Initializing Umbraco internal event handlers for cache refreshing.","SourceContext":"Umbraco.Web.Cache.DistributedCacheBinderComponent","ProcessId":14928,"ProcessName":"w3wp","ThreadId":1,"AppDomainId":2,"AppDomainAppId":"LMW3SVC2ROOT","MachineName":"DESKTOP-10GN34Q","Log4NetLevel":"INFO ","HttpRequestNumber":1,"HttpRequestId":"c0249f4d-5b93-4c68-a218-0352480ca04c"}
{"@t":"2021-01-29T10:02:03.6535001Z","@mt":"Adding examine event handlers for {RegisteredIndexers} index providers.","RegisteredIndexers":3,"SourceContext":"Umbraco.Web.Search.ExamineComponent","ProcessId":14928,"ProcessName":"w3wp","ThreadId":1,"AppDomainId":2,"AppDomainAppId":"LMW3SVC2ROOT","MachineName":"DESKTOP-10GN34Q","Log4NetLevel":"INFO ","HttpRequestNumber":1,"HttpRequestId":"c0249f4d-5b93-4c68-a218-0352480ca04c"}
{"@t":"2021-01-29T10:02:03.6971285Z","@mt":"Starting initialize async background thread.","SourceContext":"Umbraco.Web.Search.BackgroundIndexRebuilder","ProcessId":14928,"ProcessName":"w3wp","ThreadId":1,"AppDomainId":2,"AppDomainAppId":"LMW3SVC2ROOT","MachineName":"DESKTOP-10GN34Q","Log4NetLevel":"INFO ","HttpRequestNumber":1,"HttpRequestId":"c0249f4d-5b93-4c68-a218-0352480ca04c"}
{"@t":"2021-01-29T10:02:03.6981262Z","@mt":"{EndMessage} ({Duration}ms) [Timing {TimingId}]","EndMessage":"Booted.","Duration":6491,"TimingId":"6caa470","SourceContext":"Umbraco.Core.Runtime.CoreRuntime","ProcessId":14928,"ProcessName":"w3wp","ThreadId":1,"AppDomainId":2,"AppDomainAppId":"LMW3SVC2ROOT","MachineName":"DESKTOP-10GN34Q","Log4NetLevel":"INFO ","HttpRequestNumber":1,"HttpRequestId":"c0249f4d-5b93-4c68-a218-0352480ca04c"}
{"@t":"2021-01-29T10:02:04.2446635Z","@mt":"New url {Url} detected, re-discovering application url.","Url":"http://treasureroom.web.local:80/umbraco","SourceContext":"Umbraco.Core.Sync.ApplicationUrlHelper","ProcessId":14928,"ProcessName":"w3wp","ThreadId":12,"AppDomainId":2,"AppDomainAppId":"LMW3SVC2ROOT","MachineName":"DESKTOP-10GN34Q","Log4NetLevel":"INFO ","HttpRequestNumber":2,"HttpRequestId":"10c36bb7-933d-4b48-814c-13d15ef36105"}
{"@t":"2021-01-29T10:02:04.2466588Z","@mt":"ApplicationUrl: {UmbracoAppUrl} (UmbracoModule request)","UmbracoAppUrl":"http://treasureroom.web.local:80/umbraco","SourceContext":"Umbraco.Core.Sync.ApplicationUrlHelper","ProcessId":14928,"ProcessName":"w3wp","ThreadId":12,"AppDomainId":2,"AppDomainAppId":"LMW3SVC2ROOT","MachineName":"DESKTOP-10GN34Q","Log4NetLevel":"INFO ","HttpRequestNumber":2,"HttpRequestId":"10c36bb7-933d-4b48-814c-13d15ef36105"}
{"@t":"2021-01-29T10:02:12.2568562Z","@mt":"[{EventType}] Event Id: {EventId}, State: {State}","EventType":"Information","EventId":0,"State":"Login attempt succeeded for username dang.aryan@gmail.com from IP address 127.0.0.1","SourceContext":"Umbraco.Core.Logging.OwinLogger","ProcessId":14928,"ProcessName":"w3wp","ThreadId":11,"AppDomainId":2,"AppDomainAppId":"LMW3SVC2ROOT","MachineName":"DESKTOP-10GN34Q","Log4NetLevel":"INFO ","HttpRequestNumber":3,"HttpRequestId":"e27b80d6-bbb5-4c70-968d-8ef13a7f10c9"}
{"@t":"2021-01-29T10:02:12.2578552Z","@mt":"[{EventType}] Event Id: {EventId}, State: {State}","EventType":"Information","EventId":0,"State":"User: dang.aryan@gmail.com logged in from IP address 127.0.0.1","SourceContext":"Umbraco.Core.Logging.OwinLogger","ProcessId":14928,"ProcessName":"w3wp","ThreadId":11,"AppDomainId":2,"AppDomainAppId":"LMW3SVC2ROOT","MachineName":"DESKTOP-10GN34Q","Log4NetLevel":"INFO ","HttpRequestNumber":3,"HttpRequestId":"e27b80d6-bbb5-4c70-968d-8ef13a7f10c9"}
{"@t":"2021-01-29T10:05:08.6858305Z","@mt":"Scheduled health check results:","SourceContext":"Umbraco.Web.HealthCheck.HealthCheckResults","ProcessId":14928,"ProcessName":"w3wp","ThreadId":16,"AppDomainId":2,"AppDomainAppId":"LMW3SVC2ROOT","MachineName":"DESKTOP-10GN34Q","Log4NetLevel":"INFO "}
{"@t":"2021-01-29T10:05:08.6868269Z","@mt":"Checks for '{HealthCheckName}' all completed successfully.","HealthCheckName":"Folder & File Permissions","SourceContext":"Umbraco.Web.HealthCheck.HealthCheckResults","ProcessId":14928,"ProcessName":"w3wp","ThreadId":16,"AppDomainId":2,"AppDomainAppId":"LMW3SVC2ROOT","MachineName":"DESKTOP-10GN34Q","Log4NetLevel":"INFO "}
{"@t":"2021-01-29T10:05:08.6868269Z","@mt":"Result for {HealthCheckName}: {HealthCheckResult}, Message: '{HealthCheckMessage}'","HealthCheckName":"Folder & File Permissions","HealthCheckResult":"Success","HealthCheckMessage":"All folders have the correct permissions set.","SourceContext":"Umbraco.Web.HealthCheck.HealthCheckResults","ProcessId":14928,"ProcessName":"w3wp","ThreadId":16,"AppDomainId":2,"AppDomainAppId":"LMW3SVC2ROOT","MachineName":"DESKTOP-10GN34Q","Log4NetLevel":"INFO "}
{"@t":"2021-01-29T10:05:08.6868269Z","@mt":"Result for {HealthCheckName}: {HealthCheckResult}, Message: '{HealthCheckMessage}'","HealthCheckName":"Folder & File Permissions","HealthCheckResult":"Success","HealthCheckMessage":"All files have the correct permissions set.","SourceContext":"Umbraco.Web.HealthCheck.HealthCheckResults","ProcessId":14928,"ProcessName":"w3wp","ThreadId":16,"AppDomainId":2,"AppDomainAppId":"LMW3SVC2ROOT","MachineName":"DESKTOP-10GN34Q","Log4NetLevel":"INFO "}
{"@t":"2021-01-29T10:05:08.6868269Z","@mt":"Checks for '{HealthCheckName}' all completed successfully.","HealthCheckName":"SMTP Settings","SourceContext":"Umbraco.Web.HealthCheck.HealthCheckResults","ProcessId":14928,"ProcessName":"w3wp","ThreadId":16,"AppDomainId":2,"AppDomainAppId":"LMW3SVC2ROOT","MachineName":"DESKTOP-10GN34Q","Log4NetLevel":"INFO "}
{"@t":"2021-01-29T10:05:08.6868269Z","@mt":"Result for {HealthCheckName}: {HealthCheckResult}, Message: '{HealthCheckMessage}'","HealthCheckName":"SMTP Settings","HealthCheckResult":"Success","HealthCheckMessage":"SMTP settings are configured correctly and the service is operating as expected.","SourceContext":"Umbraco.Web.HealthCheck.HealthCheckResults","ProcessId":14928,"ProcessName":"w3wp","ThreadId":16,"AppDomainId":2,"AppDomainAppId":"LMW3SVC2ROOT","MachineName":"DESKTOP-10GN34Q","Log4NetLevel":"INFO "}
{"@t":"2021-01-29T10:05:08.6868269Z","@mt":"Checks for '{HealthCheckName}' completed with errors.","@l":"Warning","HealthCheckName":"Macro errors","SourceContext":"Umbraco.Web.HealthCheck.HealthCheckResults","ProcessId":14928,"ProcessName":"w3wp","ThreadId":16,"AppDomainId":2,"AppDomainAppId":"LMW3SVC2ROOT","MachineName":"DESKTOP-10GN34Q","Log4NetLevel":"WARN "}
{"@t":"2021-01-29T10:05:08.6868269Z","@mt":"Result for {HealthCheckName}: {HealthCheckResult}, Message: '{HealthCheckMessage}'","HealthCheckName":"Macro errors","HealthCheckResult":"Error","HealthCheckMessage":"MacroErrors are set to 'throw' which will prevent some or all pages in your site from loading completely if there are any errors in macros. Rectifying this will set the value to 'inline'.","SourceContext":"Umbraco.Web.HealthCheck.HealthCheckResults","ProcessId":14928,"ProcessName":"w3wp","ThreadId":16,"AppDomainId":2,"AppDomainAppId":"LMW3SVC2ROOT","MachineName":"DESKTOP-10GN34Q","Log4NetLevel":"INFO "}
{"@t":"2021-01-29T10:05:08.6868269Z","@mt":"Checks for '{HealthCheckName}' completed with errors.","@l":"Warning","HealthCheckName":"Notification Email Settings","SourceContext":"Umbraco.Web.HealthCheck.HealthCheckResults","ProcessId":14928,"ProcessName":"w3wp","ThreadId":16,"AppDomainId":2,"AppDomainAppId":"LMW3SVC2ROOT","MachineName":"DESKTOP-10GN34Q","Log4NetLevel":"WARN "}
{"@t":"2021-01-29T10:05:08.6868269Z","@mt":"Result for {HealthCheckName}: {HealthCheckResult}, Message: '{HealthCheckMessage}'","HealthCheckName":"Notification Email Settings","HealthCheckResult":"Error","HealthCheckMessage":"Notification email is still set to the default value of <strong>your@email.here</strong>.","SourceContext":"Umbraco.Web.HealthCheck.HealthCheckResults","ProcessId":14928,"ProcessName":"w3wp","ThreadId":16,"AppDomainId":2,"AppDomainAppId":"LMW3SVC2ROOT","MachineName":"DESKTOP-10GN34Q","Log4NetLevel":"INFO "}
{"@t":"2021-01-29T10:05:08.6868269Z","@mt":"Checks for '{HealthCheckName}' all completed successfully.","HealthCheckName":"Try Skip IIS Custom Errors","SourceContext":"Umbraco.Web.HealthCheck.HealthCheckResults","ProcessId":14928,"ProcessName":"w3wp","ThreadId":16,"AppDomainId":2,"AppDomainAppId":"LMW3SVC2ROOT","MachineName":"DESKTOP-10GN34Q","Log4NetLevel":"INFO "}
{"@t":"2021-01-29T10:05:08.6868269Z","@mt":"Result for {HealthCheckName}: {HealthCheckResult}, Message: '{HealthCheckMessage}'","HealthCheckName":"Try Skip IIS Custom Errors","HealthCheckResult":"Success","HealthCheckMessage":"Try Skip IIS Custom Errors is set to 'true' and you're using IIS version '10.0'.","SourceContext":"Umbraco.Web.HealthCheck.HealthCheckResults","ProcessId":14928,"ProcessName":"w3wp","ThreadId":16,"AppDomainId":2,"AppDomainAppId":"LMW3SVC2ROOT","MachineName":"DESKTOP-10GN34Q","Log4NetLevel":"INFO "}
{"@t":"2021-01-29T10:05:08.6868269Z","@mt":"Checks for '{HealthCheckName}' all completed successfully.","HealthCheckName":"Custom Errors","SourceContext":"Umbraco.Web.HealthCheck.HealthCheckResults","ProcessId":14928,"ProcessName":"w3wp","ThreadId":16,"AppDomainId":2,"AppDomainAppId":"LMW3SVC2ROOT","MachineName":"DESKTOP-10GN34Q","Log4NetLevel":"INFO "}
{"@t":"2021-01-29T10:05:08.6868269Z","@mt":"Result for {HealthCheckName}: {HealthCheckResult}, Message: '{HealthCheckMessage}'","HealthCheckName":"Custom Errors","HealthCheckResult":"Success","HealthCheckMessage":"Custom errors are set to 'RemoteOnly'.","SourceContext":"Umbraco.Web.HealthCheck.HealthCheckResults","ProcessId":14928,"ProcessName":"w3wp","ThreadId":16,"AppDomainId":2,"AppDomainAppId":"LMW3SVC2ROOT","MachineName":"DESKTOP-10GN34Q","Log4NetLevel":"INFO "}
{"@t":"2021-01-29T10:05:08.6868269Z","@mt":"Checks for '{HealthCheckName}' all completed successfully.","HealthCheckName":"Trace Mode","SourceContext":"Umbraco.Web.HealthCheck.HealthCheckResults","ProcessId":14928,"ProcessName":"w3wp","ThreadId":16,"AppDomainId":2,"AppDomainAppId":"LMW3SVC2ROOT","MachineName":"DESKTOP-10GN34Q","Log4NetLevel":"INFO "}
{"@t":"2021-01-29T10:05:08.6868269Z","@mt":"Result for {HealthCheckName}: {HealthCheckResult}, Message: '{HealthCheckMessage}'","HealthCheckName":"Trace Mode","HealthCheckResult":"Success","HealthCheckMessage":"Trace mode is disabled.","SourceContext":"Umbraco.Web.HealthCheck.HealthCheckResults","ProcessId":14928,"ProcessName":"w3wp","ThreadId":16,"AppDomainId":2,"AppDomainAppId":"LMW3SVC2ROOT","MachineName":"DESKTOP-10GN34Q","Log4NetLevel":"INFO "}
{"@t":"2021-01-29T10:05:08.6868269Z","@mt":"Checks for '{HealthCheckName}' completed with errors.","@l":"Warning","HealthCheckName":"Debug Compilation Mode","SourceContext":"Umbraco.Web.HealthCheck.HealthCheckResults","ProcessId":14928,"ProcessName":"w3wp","ThreadId":16,"AppDomainId":2,"AppDomainAppId":"LMW3SVC2ROOT","MachineName":"DESKTOP-10GN34Q","Log4NetLevel":"WARN "}
{"@t":"2021-01-29T10:05:08.6868269Z","@mt":"Result for {HealthCheckName}: {HealthCheckResult}, Message: '{HealthCheckMessage}'","HealthCheckName":"Debug Compilation Mode","HealthCheckResult":"Error","HealthCheckMessage":"Debug compilation mode is currently enabled. It is recommended to disable this setting before go live.","SourceContext":"Umbraco.Web.HealthCheck.HealthCheckResults","ProcessId":14928,"ProcessName":"w3wp","ThreadId":16,"AppDomainId":2,"AppDomainAppId":"LMW3SVC2ROOT","MachineName":"DESKTOP-10GN34Q","Log4NetLevel":"INFO "}
{"@t":"2021-01-29T10:05:08.6868269Z","@mt":"Checks for '{HealthCheckName}' completed with errors.","@l":"Warning","HealthCheckName":"Cross-site scripting Protection (X-XSS-Protection header)","SourceContext":"Umbraco.Web.HealthCheck.HealthCheckResults","ProcessId":14928,"ProcessName":"w3wp","ThreadId":16,"AppDomainId":2,"AppDomainAppId":"LMW3SVC2ROOT","MachineName":"DESKTOP-10GN34Q","Log4NetLevel":"WARN "}
{"@t":"2021-01-29T10:05:08.6868269Z","@mt":"Result for {HealthCheckName}: {HealthCheckResult}, Message: '{HealthCheckMessage}'","HealthCheckName":"Cross-site scripting Protection (X-XSS-Protection header)","HealthCheckResult":"Error","HealthCheckMessage":"The header <strong>X-XSS-Protection</strong> was not found.","SourceContext":"Umbraco.Web.HealthCheck.HealthCheckResults","ProcessId":14928,"ProcessName":"w3wp","ThreadId":16,"AppDomainId":2,"AppDomainAppId":"LMW3SVC2ROOT","MachineName":"DESKTOP-10GN34Q","Log4NetLevel":"INFO "}
{"@t":"2021-01-29T10:05:08.6868269Z","@mt":"Checks for '{HealthCheckName}' completed with errors.","@l":"Warning","HealthCheckName":"Cookie hijacking and protocol downgrade attacks Protection (Strict-Transport-Security Header (HSTS))","SourceContext":"Umbraco.Web.HealthCheck.HealthCheckResults","ProcessId":14928,"ProcessName":"w3wp","ThreadId":16,"AppDomainId":2,"AppDomainAppId":"LMW3SVC2ROOT","MachineName":"DESKTOP-10GN34Q","Log4NetLevel":"WARN "}
{"@t":"2021-01-29T10:05:08.6868269Z","@mt":"Result for {HealthCheckName}: {HealthCheckResult}, Message: '{HealthCheckMessage}'","HealthCheckName":"Cookie hijacking and protocol downgrade attacks Protection (Strict-Transport-Security Header (HSTS))","HealthCheckResult":"Error","HealthCheckMessage":"The header <strong>Strict-Transport-Security</strong> was not found.","SourceContext":"Umbraco.Web.HealthCheck.HealthCheckResults","ProcessId":14928,"ProcessName":"w3wp","ThreadId":16,"AppDomainId":2,"AppDomainAppId":"LMW3SVC2ROOT","MachineName":"DESKTOP-10GN34Q","Log4NetLevel":"INFO "}
{"@t":"2021-01-29T10:05:08.6868269Z","@mt":"Checks for '{HealthCheckName}' completed with errors.","@l":"Warning","HealthCheckName":"Content/MIME Sniffing Protection","SourceContext":"Umbraco.Web.HealthCheck.HealthCheckResults","ProcessId":14928,"ProcessName":"w3wp","ThreadId":16,"AppDomainId":2,"AppDomainAppId":"LMW3SVC2ROOT","MachineName":"DESKTOP-10GN34Q","Log4NetLevel":"WARN "}
{"@t":"2021-01-29T10:05:08.6868269Z","@mt":"Result for {HealthCheckName}: {HealthCheckResult}, Message: '{HealthCheckMessage}'","HealthCheckName":"Content/MIME Sniffing Protection","HealthCheckResult":"Error","HealthCheckMessage":"The header or meta-tag <strong>X-Content-Type-Options</strong> used to protect against MIME sniffing vulnerabilities was not found.","SourceContext":"Umbraco.Web.HealthCheck.HealthCheckResults","ProcessId":14928,"ProcessName":"w3wp","ThreadId":16,"AppDomainId":2,"AppDomainAppId":"LMW3SVC2ROOT","MachineName":"DESKTOP-10GN34Q","Log4NetLevel":"INFO "}
{"@t":"2021-01-29T10:05:08.6868269Z","@mt":"Checks for '{HealthCheckName}' all completed successfully.","HealthCheckName":"Excessive Headers","SourceContext":"Umbraco.Web.HealthCheck.HealthCheckResults","ProcessId":14928,"ProcessName":"w3wp","ThreadId":16,"AppDomainId":2,"AppDomainAppId":"LMW3SVC2ROOT","MachineName":"DESKTOP-10GN34Q","Log4NetLevel":"INFO "}
{"@t":"2021-01-29T10:05:08.6868269Z","@mt":"Result for {HealthCheckName}: {HealthCheckResult}, Message: '{HealthCheckMessage}'","HealthCheckName":"Excessive Headers","HealthCheckResult":"Success","HealthCheckMessage":"No headers revealing information about the website technology were found.","SourceContext":"Umbraco.Web.HealthCheck.HealthCheckResults","ProcessId":14928,"ProcessName":"w3wp","ThreadId":16,"AppDomainId":2,"AppDomainAppId":"LMW3SVC2ROOT","MachineName":"DESKTOP-10GN34Q","Log4NetLevel":"INFO "}
{"@t":"2021-01-29T10:05:08.6868269Z","@mt":"Checks for '{HealthCheckName}' completed with errors.","@l":"Warning","HealthCheckName":"Click-Jacking Protection","SourceContext":"Umbraco.Web.HealthCheck.HealthCheckResults","ProcessId":14928,"ProcessName":"w3wp","ThreadId":16,"AppDomainId":2,"AppDomainAppId":"LMW3SVC2ROOT","MachineName":"DESKTOP-10GN34Q","Log4NetLevel":"WARN "}
{"@t":"2021-01-29T10:05:08.6868269Z","@mt":"Result for {HealthCheckName}: {HealthCheckResult}, Message: '{HealthCheckMessage}'","HealthCheckName":"Click-Jacking Protection","HealthCheckResult":"Error","HealthCheckMessage":"The header or meta-tag <strong>X-Frame-Options</strong> used to control whether a site can be IFRAMEd by another was not found.","SourceContext":"Umbraco.Web.HealthCheck.HealthCheckResults","ProcessId":14928,"ProcessName":"w3wp","ThreadId":16,"AppDomainId":2,"AppDomainAppId":"LMW3SVC2ROOT","MachineName":"DESKTOP-10GN34Q","Log4NetLevel":"INFO "}
{"@t":"2021-01-29T10:05:08.6868269Z","@mt":"Checks for '{HealthCheckName}' completed with errors.","@l":"Warning","HealthCheckName":"HTTPS Configuration","SourceContext":"Umbraco.Web.HealthCheck.HealthCheckResults","ProcessId":14928,"ProcessName":"w3wp","ThreadId":16,"AppDomainId":2,"AppDomainAppId":"LMW3SVC2ROOT","MachineName":"DESKTOP-10GN34Q","Log4NetLevel":"WARN "}
{"@t":"2021-01-29T10:05:08.6868269Z","@mt":"Result for {HealthCheckName}: {HealthCheckResult}, Message: '{HealthCheckMessage}'","HealthCheckName":"HTTPS Configuration","HealthCheckResult":"Error","HealthCheckMessage":"You are currently not viewing the site using the HTTPS scheme.","SourceContext":"Umbraco.Web.HealthCheck.HealthCheckResults","ProcessId":14928,"ProcessName":"w3wp","ThreadId":16,"AppDomainId":2,"AppDomainAppId":"LMW3SVC2ROOT","MachineName":"DESKTOP-10GN34Q","Log4NetLevel":"INFO "}
{"@t":"2021-01-29T10:05:08.6868269Z","@mt":"Result for {HealthCheckName}: {HealthCheckResult}, Message: '{HealthCheckMessage}'","HealthCheckName":"HTTPS Configuration","HealthCheckResult":"Info","HealthCheckMessage":"The appSetting 'Umbraco.Core.UseHttps' is set to 'false' in your web.config file. Once you access this site using the HTTPS scheme, that should be set to 'true'.","SourceContext":"Umbraco.Web.HealthCheck.HealthCheckResults","ProcessId":14928,"ProcessName":"w3wp","ThreadId":16,"AppDomainId":2,"AppDomainAppId":"LMW3SVC2ROOT","MachineName":"DESKTOP-10GN34Q","Log4NetLevel":"INFO "}
{"@t":"2021-01-29T10:05:08.6868269Z","@mt":"Result for {HealthCheckName}: {HealthCheckResult}, Message: '{HealthCheckMessage}'","HealthCheckName":"HTTPS Configuration","HealthCheckResult":"Error","HealthCheckMessage":"Error pinging the URL https://treasureroom.web.local/umbraco - 'Unable to connect to the remote server'","SourceContext":"Umbraco.Web.HealthCheck.HealthCheckResults","ProcessId":14928,"ProcessName":"w3wp","ThreadId":16,"AppDomainId":2,"AppDomainAppId":"LMW3SVC2ROOT","MachineName":"DESKTOP-10GN34Q","Log4NetLevel":"INFO "}
{"@t":"2021-01-29T10:05:08.6868269Z","@mt":"Checks for '{HealthCheckName}' all completed successfully.","HealthCheckName":"Database data integrity check","SourceContext":"Umbraco.Web.HealthCheck.HealthCheckResults","ProcessId":14928,"ProcessName":"w3wp","ThreadId":16,"AppDomainId":2,"AppDomainAppId":"LMW3SVC2ROOT","MachineName":"DESKTOP-10GN34Q","Log4NetLevel":"INFO "}
{"@t":"2021-01-29T10:05:08.6868269Z","@mt":"Result for {HealthCheckName}: {HealthCheckResult}, Message: '{HealthCheckMessage}'","HealthCheckName":"Database data integrity check","HealthCheckResult":"Success","HealthCheckMessage":"<p>All document paths are valid</p>\r\n","SourceContext":"Umbraco.Web.HealthCheck.HealthCheckResults","ProcessId":14928,"ProcessName":"w3wp","ThreadId":16,"AppDomainId":2,"AppDomainAppId":"LMW3SVC2ROOT","MachineName":"DESKTOP-10GN34Q","Log4NetLevel":"INFO "}
{"@t":"2021-01-29T10:05:08.6868269Z","@mt":"Result for {HealthCheckName}: {HealthCheckResult}, Message: '{HealthCheckMessage}'","HealthCheckName":"Database data integrity check","HealthCheckResult":"Success","HealthCheckMessage":"<p>All media paths are valid</p>\r\n","SourceContext":"Umbraco.Web.HealthCheck.HealthCheckResults","ProcessId":14928,"ProcessName":"w3wp","ThreadId":16,"AppDomainId":2,"AppDomainAppId":"LMW3SVC2ROOT","MachineName":"DESKTOP-10GN34Q","Log4NetLevel":"INFO "}
{"@t":"2021-01-29T10:05:14.1417750Z","@mt":"An unhandled exception occurred","@l":"Error","@x":"System.Web.HttpCompileException (0x80004005): C:\\Users\\Aryan Dang\\Desktop\\Treasure Room\\TreasureRoom\\TreasureRoom\\Views\\Partials\\EditOrDeleteItemForm.cshtml(34): error CS1061: 'LostItemsViewModel' does not contain a definition for 'ImagePath' and no accessible extension method 'ImagePath' accepting a first argument of type 'LostItemsViewModel' could be found (are you missing a using directive or an assembly reference?)\r\n   at System.Web.Compilation.BuildManager.PostProcessFoundBuildResult(BuildResult result, Boolean keyFromVPP, VirtualPath virtualPath)\r\n   at System.Web.Compilation.BuildManager.GetBuildResultFromCacheInternal(String cacheKey, Boolean keyFromVPP, VirtualPath virtualPath, Int64 hashCode, Boolean ensureIsUpToDate)\r\n   at System.Web.Compilation.BuildManager.GetVPathBuildResultFromCacheInternal(VirtualPath virtualPath, Boolean ensureIsUpToDate)\r\n   at System.Web.Compilation.BuildManager.GetVPathBuildResultInternal(VirtualPath virtualPath, Boolean noBuild, Boolean allowCrossApp, Boolean allowBuildInPrecompile, Boolean throwIfNotFound, Boolean ensureIsUpToDate)\r\n   at System.Web.Compilation.BuildManager.GetVPathBuildResultWithNoAssert(HttpContext context, VirtualPath virtualPath, Boolean noBuild, Boolean allowCrossApp, Boolean allowBuildInPrecompile, Boolean throwIfNotFound, Boolean ensureIsUpToDate)\r\n   at System.Web.Compilation.BuildManager.GetVirtualPathObjectFactory(VirtualPath virtualPath, HttpContext context, Boolean allowCrossApp, Boolean throwIfNotFound)\r\n   at System.Web.Compilation.BuildManager.GetCompiledType(VirtualPath virtualPath)\r\n   at System.Web.Mvc.BuildManagerCompiledView.Render(ViewContext viewContext, TextWriter writer)\r\n   at Umbraco.Web.Mvc.ProfilingView.Render(ViewContext viewContext, TextWriter writer)\r\n   at System.Web.Mvc.Html.PartialExtensions.Partial(HtmlHelper htmlHelper, String partialViewName, Object model, ViewDataDictionary viewData)\r\n   at ASP._Page_Views_EditOrDeleteItemPage_cshtml.Execute() in C:\\Users\\Aryan Dang\\Desktop\\Treasure Room\\TreasureRoom\\TreasureRoom\\Views\\EditOrDeleteItemPage.cshtml:line 5\r\n   at System.Web.WebPages.WebPageBase.ExecutePageHierarchy()\r\n   at System.Web.Mvc.WebViewPage.ExecutePageHierarchy()\r\n   at System.Web.WebPages.StartPage.ExecutePageHierarchy()\r\n   at System.Web.WebPages.WebPageBase.ExecutePageHierarchy(WebPageContext pageContext, TextWriter writer, WebPageRenderingBase startPage)\r\n   at Umbraco.Web.Mvc.ProfilingView.Render(ViewContext viewContext, TextWriter writer)\r\n   at System.Web.Mvc.ViewResultBase.ExecuteResult(ControllerContext context)\r\n   at System.Web.Mvc.ControllerActionInvoker.InvokeActionResultFilterRecursive(IList`1 filters, Int32 filterIndex, ResultExecutingContext preContext, ControllerContext controllerContext, ActionResult actionResult)\r\n   at System.Web.Mvc.ControllerActionInvoker.InvokeActionResultFilterRecursive(IList`1 filters, Int32 filterIndex, ResultExecutingContext preContext, ControllerContext controllerContext, ActionResult actionResult)\r\n   at System.Web.Mvc.ControllerActionInvoker.InvokeActionResultFilterRecursive(IList`1 filters, Int32 filterIndex, ResultExecutingContext preContext, ControllerContext controllerContext, ActionResult actionResult)\r\n   at System.Web.Mvc.ControllerActionInvoker.InvokeActionResultFilterRecursive(IList`1 filters, Int32 filterIndex, ResultExecutingContext preContext, ControllerContext controllerContext, ActionResult actionResult)\r\n   at System.Web.Mvc.ControllerActionInvoker.InvokeActionResultWithFilters(ControllerContext controllerContext, IList`1 filters, ActionResult actionResult)\r\n   at System.Web.Mvc.Async.AsyncControllerActionInvoker.<>c__DisplayClass3_1.<BeginInvokeAction>b__1(IAsyncResult asyncResult)\r\n   at System.Web.Mvc.Async.AsyncControllerActionInvoker.EndInvokeAction(IAsyncResult asyncResult)\r\n   at System.Web.Mvc.Controller.<>c.<BeginExecuteCore>b__152_1(IAsyncResult asyncResult, ExecuteCoreState innerState)\r\n   at System.Web.Mvc.Async.AsyncResultWrapper.WrappedAsyncVoid`1.CallEndDelegate(IAsyncResult asyncResult)\r\n   at System.Web.Mvc.Controller.EndExecuteCore(IAsyncResult asyncResult)\r\n   at System.Web.Mvc.Async.AsyncResultWrapper.WrappedAsyncVoid`1.CallEndDelegate(IAsyncResult asyncResult)\r\n   at System.Web.Mvc.Controller.EndExecute(IAsyncResult asyncResult)\r\n   at System.Web.Mvc.MvcHandler.<>c.<BeginProcessRequest>b__20_1(IAsyncResult asyncResult, ProcessRequestState innerState)\r\n   at System.Web.Mvc.Async.AsyncResultWrapper.WrappedAsyncVoid`1.CallEndDelegate(IAsyncResult asyncResult)\r\n   at System.Web.Mvc.MvcHandler.EndProcessRequest(IAsyncResult asyncResult)\r\n   at System.Web.HttpApplication.CallHandlerExecutionStep.System.Web.HttpApplication.IExecutionStep.Execute()\r\n   at System.Web.HttpApplication.ExecuteStepImpl(IExecutionStep step)\r\n   at System.Web.Mvc.Async.AsyncControllerActionInvoker.<>c__DisplayClass3_1.<BeginInvokeAction>b__1(IAsyncResult asyncResult)\r\n   at System.Web.Mvc.Async.AsyncControllerActionInvoker.EndInvokeAction(IAsyncResult asyncResult)\r\n   at System.Web.Mvc.Controller.<>c.<BeginExecuteCore>b__152_1(IAsyncResult asyncResult, ExecuteCoreState innerState)\r\n   at System.Web.Mvc.Async.AsyncResultWrapper.WrappedAsyncVoid`1.CallEndDelegate(IAsyncResult asyncResult)\r\n   at System.Web.Mvc.Controller.EndExecuteCore(IAsyncResult asyncResult)\r\n   at System.Web.Mvc.Async.AsyncResultWrapper.WrappedAsyncVoid`1.CallEndDelegate(IAsyncResult asyncResult)\r\n   at System.Web.Mvc.Controller.EndExecute(IAsyncResult asyncResult)\r\n   at System.Web.Mvc.MvcHandler.<>c.<BeginProcessRequest>b__20_1(IAsyncResult asyncResult, ProcessRequestState innerState)\r\n   at System.Web.Mvc.Async.AsyncResultWrapper.WrappedAsyncVoid`1.CallEndDelegate(IAsyncResult asyncResult)\r\n   at System.Web.Mvc.MvcHandler.EndProcessRequest(IAsyncResult asyncResult)\r\n   at System.Web.HttpApplication.CallHandlerExecutionStep.System.Web.HttpApplication.IExecutionStep.Execute()\r\n   at System.Web.HttpApplication.ExecuteStepImpl(IExecutionStep step)\r\n   at System.Web.HttpApplication.ExecuteStep(IExecutionStep step, Boolean& completedSynchronously)","SourceContext":"Umbraco.Web.UmbracoApplicationBase","ProcessId":14928,"ProcessName":"w3wp","ThreadId":12,"AppDomainId":2,"AppDomainAppId":"LMW3SVC2ROOT","MachineName":"DESKTOP-10GN34Q","Log4NetLevel":"ERROR","HttpSessionId":"fn1mgrysjnbxtr5og4dl4g3s","HttpRequestNumber":4,"HttpRequestId":"d74404fa-a5ea-4182-82d7-a0bbf95ad9c1"}
{"@t":"2021-01-29T10:05:14.1417750Z","@mt":"An unhandled exception occurred","@l":"Error","@x":"System.Web.HttpCompileException (0x80004005): C:\\Users\\Aryan Dang\\Desktop\\Treasure Room\\TreasureRoom\\TreasureRoom\\Views\\Partials\\EditOrDeleteItemForm.cshtml(34): error CS1061: 'LostItemsViewModel' does not contain a definition for 'ImagePath' and no accessible extension method 'ImagePath' accepting a first argument of type 'LostItemsViewModel' could be found (are you missing a using directive or an assembly reference?)\r\n   at System.Web.Compilation.BuildManager.PostProcessFoundBuildResult(BuildResult result, Boolean keyFromVPP, VirtualPath virtualPath)\r\n   at System.Web.Compilation.BuildManager.GetBuildResultFromCacheInternal(String cacheKey, Boolean keyFromVPP, VirtualPath virtualPath, Int64 hashCode, Boolean ensureIsUpToDate)\r\n   at System.Web.Compilation.BuildManager.GetVPathBuildResultFromCacheInternal(VirtualPath virtualPath, Boolean ensureIsUpToDate)\r\n   at System.Web.Compilation.BuildManager.GetVPathBuildResultInternal(VirtualPath virtualPath, Boolean noBuild, Boolean allowCrossApp, Boolean allowBuildInPrecompile, Boolean throwIfNotFound, Boolean ensureIsUpToDate)\r\n   at System.Web.Compilation.BuildManager.GetVPathBuildResultWithNoAssert(HttpContext context, VirtualPath virtualPath, Boolean noBuild, Boolean allowCrossApp, Boolean allowBuildInPrecompile, Boolean throwIfNotFound, Boolean ensureIsUpToDate)\r\n   at System.Web.Compilation.BuildManager.GetVirtualPathObjectFactory(VirtualPath virtualPath, HttpContext context, Boolean allowCrossApp, Boolean throwIfNotFound)\r\n   at System.Web.Compilation.BuildManager.GetCompiledType(VirtualPath virtualPath)\r\n   at System.Web.Mvc.BuildManagerCompiledView.Render(ViewContext viewContext, TextWriter writer)\r\n   at Umbraco.Web.Mvc.ProfilingView.Render(ViewContext viewContext, TextWriter writer)\r\n   at System.Web.Mvc.Html.PartialExtensions.Partial(HtmlHelper htmlHelper, String partialViewName, Object model, ViewDataDictionary viewData)\r\n   at ASP._Page_Views_EditOrDeleteItemPage_cshtml.Execute() in C:\\Users\\Aryan Dang\\Desktop\\Treasure Room\\TreasureRoom\\TreasureRoom\\Views\\EditOrDeleteItemPage.cshtml:line 5\r\n   at System.Web.WebPages.WebPageBase.ExecutePageHierarchy()\r\n   at System.Web.Mvc.WebViewPage.ExecutePageHierarchy()\r\n   at System.Web.WebPages.StartPage.ExecutePageHierarchy()\r\n   at System.Web.WebPages.WebPageBase.ExecutePageHierarchy(WebPageContext pageContext, TextWriter writer, WebPageRenderingBase startPage)\r\n   at Umbraco.Web.Mvc.ProfilingView.Render(ViewContext viewContext, TextWriter writer)\r\n   at System.Web.Mvc.ViewResultBase.ExecuteResult(ControllerContext context)\r\n   at System.Web.Mvc.ControllerActionInvoker.InvokeActionResultFilterRecursive(IList`1 filters, Int32 filterIndex, ResultExecutingContext preContext, ControllerContext controllerContext, ActionResult actionResult)\r\n   at System.Web.Mvc.ControllerActionInvoker.InvokeActionResultFilterRecursive(IList`1 filters, Int32 filterIndex, ResultExecutingContext preContext, ControllerContext controllerContext, ActionResult actionResult)\r\n   at System.Web.Mvc.ControllerActionInvoker.InvokeActionResultFilterRecursive(IList`1 filters, Int32 filterIndex, ResultExecutingContext preContext, ControllerContext controllerContext, ActionResult actionResult)\r\n   at System.Web.Mvc.ControllerActionInvoker.InvokeActionResultFilterRecursive(IList`1 filters, Int32 filterIndex, ResultExecutingContext preContext, ControllerContext controllerContext, ActionResult actionResult)\r\n   at System.Web.Mvc.ControllerActionInvoker.InvokeActionResultWithFilters(ControllerContext controllerContext, IList`1 filters, ActionResult actionResult)\r\n   at System.Web.Mvc.Async.AsyncControllerActionInvoker.<>c__DisplayClass3_1.<BeginInvokeAction>b__1(IAsyncResult asyncResult)\r\n   at System.Web.Mvc.Async.AsyncControllerActionInvoker.EndInvokeAction(IAsyncResult asyncResult)\r\n   at System.Web.Mvc.Controller.<>c.<BeginExecuteCore>b__152_1(IAsyncResult asyncResult, ExecuteCoreState innerState)\r\n   at System.Web.Mvc.Async.AsyncResultWrapper.WrappedAsyncVoid`1.CallEndDelegate(IAsyncResult asyncResult)\r\n   at System.Web.Mvc.Controller.EndExecuteCore(IAsyncResult asyncResult)\r\n   at System.Web.Mvc.Async.AsyncResultWrapper.WrappedAsyncVoid`1.CallEndDelegate(IAsyncResult asyncResult)\r\n   at System.Web.Mvc.Controller.EndExecute(IAsyncResult asyncResult)\r\n   at System.Web.Mvc.MvcHandler.<>c.<BeginProcessRequest>b__20_1(IAsyncResult asyncResult, ProcessRequestState innerState)\r\n   at System.Web.Mvc.Async.AsyncResultWrapper.WrappedAsyncVoid`1.CallEndDelegate(IAsyncResult asyncResult)\r\n   at System.Web.Mvc.MvcHandler.EndProcessRequest(IAsyncResult asyncResult)\r\n   at System.Web.HttpApplication.CallHandlerExecutionStep.System.Web.HttpApplication.IExecutionStep.Execute()\r\n   at System.Web.HttpApplication.ExecuteStepImpl(IExecutionStep step)\r\n   at System.Web.Mvc.Async.AsyncControllerActionInvoker.<>c__DisplayClass3_1.<BeginInvokeAction>b__1(IAsyncResult asyncResult)\r\n   at System.Web.Mvc.Async.AsyncControllerActionInvoker.EndInvokeAction(IAsyncResult asyncResult)\r\n   at System.Web.Mvc.Controller.<>c.<BeginExecuteCore>b__152_1(IAsyncResult asyncResult, ExecuteCoreState innerState)\r\n   at System.Web.Mvc.Async.AsyncResultWrapper.WrappedAsyncVoid`1.CallEndDelegate(IAsyncResult asyncResult)\r\n   at System.Web.Mvc.Controller.EndExecuteCore(IAsyncResult asyncResult)\r\n   at System.Web.Mvc.Async.AsyncResultWrapper.WrappedAsyncVoid`1.CallEndDelegate(IAsyncResult asyncResult)\r\n   at System.Web.Mvc.Controller.EndExecute(IAsyncResult asyncResult)\r\n   at System.Web.Mvc.MvcHandler.<>c.<BeginProcessRequest>b__20_1(IAsyncResult asyncResult, ProcessRequestState innerState)\r\n   at System.Web.Mvc.Async.AsyncResultWrapper.WrappedAsyncVoid`1.CallEndDelegate(IAsyncResult asyncResult)\r\n   at System.Web.Mvc.MvcHandler.EndProcessRequest(IAsyncResult asyncResult)\r\n   at System.Web.HttpApplication.CallHandlerExecutionStep.System.Web.HttpApplication.IExecutionStep.Execute()\r\n   at System.Web.HttpApplication.ExecuteStepImpl(IExecutionStep step)\r\n   at System.Web.HttpApplication.ExecuteStep(IExecutionStep step, Boolean& completedSynchronously)","SourceContext":"Umbraco.Web.UmbracoApplicationBase","ProcessId":14928,"ProcessName":"w3wp","ThreadId":39,"AppDomainId":2,"AppDomainAppId":"LMW3SVC2ROOT","MachineName":"DESKTOP-10GN34Q","Log4NetLevel":"ERROR","HttpSessionId":"lbulkrkla2jurdiykxmvv5ze","HttpRequestNumber":5,"HttpRequestId":"5cfad5b9-8e67-449b-9806-2799b0b60ee1"}
{"@t":"2021-01-29T10:21:41.2384352Z","@mt":"[{EventType}] Event Id: {EventId}, State: {State}","EventType":"Information","EventId":0,"State":"User logged will be logged out due to timeout: dang.aryan@gmail.com, IP Address: 127.0.0.1","SourceContext":"Umbraco.Core.Logging.OwinLogger","ProcessId":14928,"ProcessName":"w3wp","ThreadId":159,"AppDomainId":2,"AppDomainAppId":"LMW3SVC2ROOT","MachineName":"DESKTOP-10GN34Q","Log4NetLevel":"INFO ","HttpRequestNumber":6,"HttpRequestId":"4c3c196f-64c6-4824-b1eb-40f0b4e0e5c1"}
{"@t":"2021-01-29T10:55:09.5490137Z","@mt":"[{EventType}] Event Id: {EventId}, State: {State}","EventType":"Information","EventId":0,"State":"Login attempt succeeded for username dang.aryan@gmail.com from IP address 127.0.0.1","SourceContext":"Umbraco.Core.Logging.OwinLogger","ProcessId":14928,"ProcessName":"w3wp","ThreadId":289,"AppDomainId":2,"AppDomainAppId":"LMW3SVC2ROOT","MachineName":"DESKTOP-10GN34Q","Log4NetLevel":"INFO ","HttpRequestNumber":7,"HttpRequestId":"c1459909-6b38-4980-a295-4a8ca97e02e7"}
{"@t":"2021-01-29T10:55:09.5490137Z","@mt":"[{EventType}] Event Id: {EventId}, State: {State}","EventType":"Information","EventId":0,"State":"User: dang.aryan@gmail.com logged in from IP address 127.0.0.1","SourceContext":"Umbraco.Core.Logging.OwinLogger","ProcessId":14928,"ProcessName":"w3wp","ThreadId":289,"AppDomainId":2,"AppDomainAppId":"LMW3SVC2ROOT","MachineName":"DESKTOP-10GN34Q","Log4NetLevel":"INFO ","HttpRequestNumber":7,"HttpRequestId":"c1459909-6b38-4980-a295-4a8ca97e02e7"}
{"@t":"2021-01-29T11:14:41.4632798Z","@mt":"[{EventType}] Event Id: {EventId}, State: {State}","EventType":"Information","EventId":0,"State":"User logged will be logged out due to timeout: dang.aryan@gmail.com, IP Address: 127.0.0.1","SourceContext":"Umbraco.Core.Logging.OwinLogger","ProcessId":14928,"ProcessName":"w3wp","ThreadId":288,"AppDomainId":2,"AppDomainAppId":"LMW3SVC2ROOT","MachineName":"DESKTOP-10GN34Q","Log4NetLevel":"INFO ","HttpRequestNumber":8,"HttpRequestId":"0b5d86b9-a58c-40c1-ad45-8bb293c4485b"}
{"@t":"2021-01-29T12:00:13.6627364Z","@mt":"Failed (will repeat).","@l":"Error","@x":"System.Data.SqlClient.SqlException (0x80131904): SHUTDOWN is in progress.\r\nLogin failed for user 'TreasureRoomDB_admin'.\r\nCannot continue the execution because the session is in the kill state.\r\nA severe error occurred on the current command.  The results, if any, should be discarded.\r\n   at System.Data.SqlClient.SqlConnection.OnError(SqlException exception, Boolean breakConnection, Action`1 wrapCloseInAction)\r\n   at System.Data.SqlClient.TdsParser.ThrowExceptionAndWarning(TdsParserStateObject stateObj, Boolean callerHasConnectionLock, Boolean asyncClose)\r\n   at System.Data.SqlClient.TdsParser.TryRun(RunBehavior runBehavior, SqlCommand cmdHandler, SqlDataReader dataStream, BulkCopySimpleResultSet bulkCopyHandler, TdsParserStateObject stateObj, Boolean& dataReady)\r\n   at System.Data.SqlClient.TdsParser.Run(RunBehavior runBehavior, SqlCommand cmdHandler, SqlDataReader dataStream, BulkCopySimpleResultSet bulkCopyHandler, TdsParserStateObject stateObj)\r\n   at System.Data.SqlClient.TdsParser.TdsExecuteTransactionManagerRequest(Byte[] buffer, TransactionManagerRequestType request, String transactionName, TransactionManagerIsolationLevel isoLevel, Int32 timeout, SqlInternalTransaction transaction, TdsParserStateObject stateObj, Boolean isDelegateControlRequest)\r\n   at System.Data.SqlClient.SqlInternalConnectionTds.ExecuteTransactionYukon(TransactionRequest transactionRequest, String transactionName, IsolationLevel iso, SqlInternalTransaction internalTransaction, Boolean isDelegateControlRequest)\r\n   at System.Data.SqlClient.SqlInternalConnection.BeginSqlTransaction(IsolationLevel iso, String transactionName, Boolean shouldReconnect)\r\n   at System.Data.SqlClient.SqlConnection.BeginTransaction(IsolationLevel iso, String transactionName)\r\n   at System.Data.SqlClient.SqlConnection.BeginDbTransaction(IsolationLevel isolationLevel)\r\n   at StackExchange.Profiling.Data.ProfiledDbConnection.BeginDbTransaction(IsolationLevel isolationLevel) in C:\\projects\\dotnet\\src\\MiniProfiler.Shared\\Data\\ProfiledDbConnection.cs:line 138\r\n   at NPoco.Database.BeginTransaction(IsolationLevel isolationLevel)\r\n   at Umbraco.Core.Scoping.Scope.get_Database()\r\n   at Umbraco.Core.Sync.DatabaseServerMessenger.Sync()\r\n   at Umbraco.Web.Compose.DatabaseServerRegistrarAndMessengerComponent.InstructionProcessTask.PerformRun()\r\nClientConnectionId:833edc23-bf70-4992-9f20-38c5ae9f3552\r\nError Number:6005,State:1,Class:14","SourceContext":"Umbraco.Web.Compose.DatabaseServerRegistrarAndMessengerComponent+InstructionProcessTask","ProcessId":14928,"ProcessName":"w3wp","ThreadId":309,"AppDomainId":2,"AppDomainAppId":"LMW3SVC2ROOT","MachineName":"DESKTOP-10GN34Q","Log4NetLevel":"ERROR"}
